x_make_py_mod_sideload_x/__init__.py
x_make_py_mod_sideload_x/x_cls_make_py_mod_sideload_x.py
x_make_py_mod_sideload_x-12.0.2.dist-info/METADATA
x_make_py_mod_sideload_x-12.0.2.dist-info/WHEEL
x_make_py_mod_sideload_x-12.0.2.dist-info/top_level.txt
x_make_py_mod_sideload_x-12.0.2.dist-info/RECORD
