Metadata-Version: 2.4
Name: x_make_py_mod_sideload_x
Version: 12.0.2
Summary: Python module sideloader.
Author-email: RRGM of the Primus Pilus Night Watch AI Corporation <eye4357@outlook.com>
License-Expression: MIT
